vppopt/__init__.py
vppopt/nodes_utils.py
vppopt/results.py
vppopt/schemas.py
vppopt/utils.py
vppopt/vppopt.py
vppopt/vppopt_schema.json
vppopt/workflow.py
vppopt/components/__init__.py
vppopt/interfaces/__init__.py
vppopt/interfaces/cli.py
vppopt-0.1.1.dist-info/LICENSE
vppopt-0.1.1.dist-info/METADATA
vppopt-0.1.1.dist-info/WHEEL
vppopt-0.1.1.dist-info/entry_points.txt
vppopt-0.1.1.dist-info/top_level.txt
vppopt-0.1.1.dist-info/RECORD
