Metadata-Version: 2.1
Name: vppopt
Version: 0.1.1
Summary: Virtual Power Plant Optimization Platform
Home-page: https://github.com/cenaero-enb/h2cs-design
Author: Long Le
Author-email: vanlong.le@cenaero.be
License: Apache Software License 2.0
Keywords: vppopt
Platform: UNKNOWN
Classifier: License :: OSI Approved :: MIT License
Classifier: Operating System :: Unix
Classifier: Operating System :: POSIX
Classifier: Operating System :: Microsoft :: Windows
Classifier: Operating System :: MacOS
Classifier: Operating System :: OS Independent
Classifier: Programming Language :: Python
Classifier: Programming Language :: Python :: 3
Classifier: Programming Language :: Python :: 3.7
Classifier: Programming Language :: Python :: 3.8
Classifier: Programming Language :: Python :: 3.9
Classifier: Programming Language :: Python :: Implementation :: CPython
Requires-Python: >=3.6.0
License-File: LICENSE
Requires-Dist: pyomo (==5.7.2)
Requires-Dist: pandas
Requires-Dist: openpyxl
Requires-Dist: xlrd
Requires-Dist: matplotlib
Requires-Dist: python-jsonschema-objects
Requires-Dist: xlsxwriter
Requires-Dist: loguru
Requires-Dist: oemof.solph
Requires-Dist: pymoo
Requires-Dist: xmltodict
